[{"company":{"name":"TNL Mediagene","logo":"https://s3-symbol-logo.tradingview.com/tnl-mediagene.svg"},"country":{"name":"Taiwan","flag":"https://s3-symbol-logo.tradingview.com/country/TW.svg"},"exchange":"NASDAQ","industry":"Internet software/Services","key":"NASDAQ:TNMG","sector":"Technology services","symbol":"TNMG","date":"2025-10-08T13:30:00.000Z","volume":{"one":67247900,"five":147201700,"ten":169449500,"twenty":263220200,"fifty":286800300},"price":{"high":0.5600000023841858,"open":0.3709999918937683,"close":0.47999998927116394,"low":0.36399999260902405},"ema":{"fifty":0.38093093642087067,"five":0.36448940980537653,"ten":0.334204552437256,"twenty":0.32962837614182505},"below":{"fifty":0,"five":0,"ten":0,"twenty":0},"kdj":{"d":36.98269534914022,"j":74.29196839658654,"k":49.419119698288995},"kc":{"lower":0.053814787225019256,"mid":0.32962837614182505,"upper":0.6054419650586309},"rating":"strong-buy"},{"company":{"name":"Genprex, Inc.","logo":"https://s3-symbol-logo.tradingview.com/genprex.svg"},"country":{"name":"United States","flag":"https://s3-symbol-logo.tradingview.com/country/US.svg"},"exchange":"NASDAQ","industry":"Pharmaceuticals: major","key":"NASDAQ:GNPX","sector":"Health technology","symbol":"GNPX","date":"2025-10-08T13:30:00.000Z","volume":{"one":5360600,"five":21092300,"ten":38971000,"twenty":77388500,"fifty":558464100},"price":{"high":0.24500000476837158,"open":0.20100000500679016,"close":0.24400000274181366,"low":0.20100000500679016},"ema":{"fifty":0.21735050108210802,"five":0.21237348964357963,"ten":0.2060335323155796,"twenty":0.20713912754120398},"below":{"fifty":0,"five":0,"ten":0,"twenty":0},"kdj":{"d":46.39103603331275,"j":109.33171570616135,"k":67.37126259092895},"kc":{"lower":0.08105692919222432,"mid":0.20713912754120398,"upper":0.3332213258901836},"rating":"neutral"},{"company":{"name":"Klotho Neurosciences, Inc.","logo":"https://s3-symbol-logo.tradingview.com/klotho-neurosciences.svg"},"country":{"name":"United States","flag":"https://s3-symbol-logo.tradingview.com/country/US.svg"},"exchange":"NASDAQ","industry":"Miscellaneous commercial services","key":"NASDAQ:KLTO","sector":"Commercial services","symbol":"KLTO","date":"2025-10-08T13:30:00.000Z","volume":{"one":4972400,"five":17371800,"ten":37902700,"twenty":53777700,"fifty":119986900},"price":{"high":0.6100000143051147,"open":0.5830000042915344,"close":0.5799999833106995,"low":0.5249999761581421},"ema":{"fifty":0.6526885865300598,"five":0.544460496069253,"ten":0.5278006934649841,"twenty":0.5443324052967556},"below":{"fifty":44,"five":0,"ten":0,"twenty":0},"kdj":{"d":48.10843579751044,"j":105.77556756867156,"k":67.33081305456415},"kc":{"lower":0.3044981458473113,"mid":0.5443324052967556,"upper":0.7841666647462},"rating":"neutral"},{"company":{"name":"Longeveron Inc.","logo":"https://s3-symbol-logo.tradingview.com/longeveron.svg"},"country":{"name":"United States","flag":"https://s3-symbol-logo.tradingview.com/country/US.svg"},"exchange":"NASDAQ","industry":"Biotechnology","key":"NASDAQ:LGVN","sector":"Health technology","symbol":"LGVN","date":"2025-10-08T13:30:00.000Z","volume":{"one":2150600,"five":3461700,"ten":4954500,"twenty":8354500,"fifty":52276200},"price":{"high":0.9399999976158142,"open":0.8100000023841858,"close":0.9269999861717224,"low":0.8100000023841858},"ema":{"fifty":0.913892417232783,"five":0.8345242253554862,"ten":0.808699514215507,"twenty":0.8059682168764856},"below":{"fifty":0,"five":0,"ten":0,"twenty":0},"kdj":{"d":58.62881969833356,"j":103.18893517173282,"k":73.48219152279998},"kc":{"lower":0.6068242264494934,"mid":0.8059682168764856,"upper":1.0051122073034777},"rating":"strong-buy"},{"company":{"name":"Fury Gold Mines Limited","logo":"https://s3-symbol-logo.tradingview.com/fury-gold-mines-limited.svg"},"country":{"name":"Canada","flag":"https://s3-symbol-logo.tradingview.com/country/CA.svg"},"exchange":"AMEX","industry":"Precious metals","key":"AMEX:FURY","sector":"Non-energy minerals","symbol":"FURY","date":"2025-10-08T13:30:00.000Z","volume":{"one":1634100,"five":4979800,"ten":8084500,"twenty":13384800,"fifty":27534800},"price":{"high":0.7170000076293945,"open":0.6399999856948853,"close":0.7149999737739563,"low":0.6349999904632568},"ema":{"fifty":0.6069543615603376,"five":0.6614198521452234,"ten":0.6562709862846873,"twenty":0.6489162021819478},"below":{"fifty":0,"five":0,"ten":0,"twenty":0},"kdj":{"d":36.51639620763203,"j":73.62488818261602,"k":48.885893532626696},"kc":{"lower":0.4565095849488441,"mid":0.6489162021819478,"upper":0.8413228194150515},"rating":"strong-buy"},{"company":{"name":"Co-Diagnostics, Inc.","logo":"https://s3-symbol-logo.tradingview.com/co-diagnostics.svg"},"country":{"name":"United States","flag":"https://s3-symbol-logo.tradingview.com/country/US.svg"},"exchange":"NASDAQ","industry":"Biotechnology","key":"NASDAQ:CODX","sector":"Health technology","symbol":"CODX","date":"2025-10-08T13:30:00.000Z","volume":{"one":768100,"five":4523300,"ten":11227400,"twenty":291048200,"fifty":399981300},"price":{"high":0.39899998903274536,"open":0.3619999885559082,"close":0.39399999380111694,"low":0.35100001096725464},"ema":{"fifty":0.34894272707690316,"five":0.3805123915354882,"ten":0.37961887970195907,"twenty":0.3753422749193827},"below":{"fifty":0,"five":0,"ten":0,"twenty":0},"kdj":{"d":42.40095010629021,"j":89.42077708249553,"k":58.07422576502532},"kc":{"lower":0.18151111807432768,"mid":0.3753422749193827,"upper":0.5691734317644377},"rating":"buy"},{"company":{"name":"Cue Biopharma, Inc.","logo":"https://s3-symbol-logo.tradingview.com/cue-biopharma.svg"},"country":{"name":"United States","flag":"https://s3-symbol-logo.tradingview.com/country/US.svg"},"exchange":"NASDAQ","industry":"Biotechnology","key":"NASDAQ:CUE","sector":"Health technology","symbol":"CUE","date":"2025-10-08T13:30:00.000Z","volume":{"one":597300,"five":1512300,"ten":2820300,"twenty":4412500,"fifty":8033000},"price":{"high":0.8600000143051147,"open":0.7799999713897705,"close":0.8579999804496765,"low":0.7670000195503235},"ema":{"fifty":0.7583851348054418,"five":0.7746843121244967,"ten":0.751021778918903,"twenty":0.7452568090440091},"below":{"fifty":0,"five":0,"ten":0,"twenty":0},"kdj":{"d":63.92465439401725,"j":105.00172492514,"k":77.61701123772484},"kc":{"lower":0.5577804382092436,"mid":0.7452568090440091,"upper":0.9327331798787747},"rating":"strong-buy"},{"company":{"name":"Tianci International, Inc.","logo":"https://s3-symbol-logo.tradingview.com/tianci-international.svg"},"country":{"name":"Hong Kong","flag":"https://s3-symbol-logo.tradingview.com/country/HK.svg"},"exchange":"NASDAQ","industry":"Financial conglomerates","key":"NASDAQ:CIIT","sector":"Finance","symbol":"CIIT","date":"2025-10-08T13:30:00.000Z","volume":{"one":564700,"five":1403600,"ten":1972200,"twenty":6261800,"fifty":9028000},"price":{"high":0.8379999995231628,"open":0.8069999814033508,"close":0.7960000038146973,"low":0.7670000195503235},"ema":{"fifty":0.8706630578702793,"five":0.727413723746836,"ten":0.6965024724803169,"twenty":0.7099829814011595},"below":{"fifty":16,"five":0,"ten":0,"twenty":0},"kdj":{"d":52.831183626209835,"j":112.63132585911421,"k":72.7645643705113},"kc":{"lower":0.2501111351676729,"mid":0.7099829814011595,"upper":1.169854827634646},"rating":"neutral"},{"company":{"name":"Virax Biolabs Group Limited","logo":"https://s3-symbol-logo.tradingview.com/virax-biolabs-limited.svg"},"country":{"name":"United Kingdom","flag":"https://s3-symbol-logo.tradingview.com/country/GB.svg"},"exchange":"NASDAQ","industry":"Financial conglomerates","key":"NASDAQ:VRAX","sector":"Finance","symbol":"VRAX","date":"2025-10-08T13:30:00.000Z","volume":{"one":529300,"five":1045600,"ten":1609600,"twenty":7321900,"fifty":36266400},"price":{"high":0.6899999976158142,"open":0.6399999856948853,"close":0.6819999814033508,"low":0.6349999904632568},"ema":{"fifty":0.6893354697899513,"five":0.6451190737450225,"ten":0.6337202803757699,"twenty":0.6329808744036206},"below":{"fifty":0,"five":0,"ten":0,"twenty":0},"kdj":{"d":50.41943722384375,"j":97.84840035919977,"k":66.22909160229575},"kc":{"lower":0.4803000945280471,"mid":0.6329808744036206,"upper":0.7856616542791941},"rating":"neutral"},{"company":{"name":"Fenbo Holdings Limited","logo":"https://s3-symbol-logo.tradingview.com/fenbo-limited.svg"},"country":{"name":"Hong Kong","flag":"https://s3-symbol-logo.tradingview.com/country/HK.svg"},"exchange":"NASDAQ","industry":"Electronics/Appliances","key":"NASDAQ:FEBO","sector":"Consumer durables","symbol":"FEBO","date":"2025-10-08T13:30:00.000Z","volume":{"one":23500,"five":314800,"ten":519900,"twenty":984400,"fifty":10193000},"price":{"high":0.7889999747276306,"open":0.699999988079071,"close":0.7789999842643738,"low":0.699999988079071},"ema":{"fifty":0.7875098360390208,"five":0.7452183343525518,"ten":0.7366809034241252,"twenty":0.7381902024640452},"below":{"fifty":0,"five":0,"ten":0,"twenty":0},"kdj":{"d":55.34612062595845,"j":82.95848984317894,"k":64.55024369836528},"kc":{"lower":0.3669016751454361,"mid":0.7381902024640452,"upper":1.1094787297826543},"rating":"neutral"}]